odoo/addons/product_sold_by_delivery_week/README.rst
odoo/addons/product_sold_by_delivery_week/__init__.py
odoo/addons/product_sold_by_delivery_week/__manifest__.py
odoo/addons/product_sold_by_delivery_week/hooks.py
odoo/addons/product_sold_by_delivery_week/data/ir_cron.xml
odoo/addons/product_sold_by_delivery_week/i18n/es.po
odoo/addons/product_sold_by_delivery_week/i18n/product_sold_by_delivery_week.pot
odoo/addons/product_sold_by_delivery_week/models/__init__.py
odoo/addons/product_sold_by_delivery_week/models/product_product.py
odoo/addons/product_sold_by_delivery_week/models/product_template.py
odoo/addons/product_sold_by_delivery_week/models/sale_order.py
odoo/addons/product_sold_by_delivery_week/models/stock_move.py
odoo/addons/product_sold_by_delivery_week/readme/CONFIGURE.rst
odoo/addons/product_sold_by_delivery_week/readme/CONTRIBUTORS.rst
odoo/addons/product_sold_by_delivery_week/readme/DESCRIPTION.rst
odoo/addons/product_sold_by_delivery_week/readme/ROADMAP.rst
odoo/addons/product_sold_by_delivery_week/readme/USAGE.rst
odoo/addons/product_sold_by_delivery_week/security/product_sold_by_delivery_week_security.xml
odoo/addons/product_sold_by_delivery_week/static/description/icon.png
odoo/addons/product_sold_by_delivery_week/static/description/index.html
odoo/addons/product_sold_by_delivery_week/static/description/sold_by_week_hint.png
odoo/addons/product_sold_by_delivery_week/tests/__init__.py
odoo/addons/product_sold_by_delivery_week/views/product_views.xml
odoo/addons/product_sold_by_delivery_week/views/sale_views.xml
odoo13_addon_product_sold_by_delivery_week-13.0.1.1.3.dist-info/METADATA
odoo13_addon_product_sold_by_delivery_week-13.0.1.1.3.dist-info/WHEEL
odoo13_addon_product_sold_by_delivery_week-13.0.1.1.3.dist-info/top_level.txt
odoo13_addon_product_sold_by_delivery_week-13.0.1.1.3.dist-info/RECORD
